caft/__about__.py
caft/__init__.py
caft/core.py
caft/logging.py
caft_llm-0.0.1.dist-info/METADATA
caft_llm-0.0.1.dist-info/WHEEL
caft_llm-0.0.1.dist-info/licenses/LICENSE.txt
caft_llm-0.0.1.dist-info/RECORD
