Metadata-Version: 2.4
Name: caft-llm
Version: 0.0.1
Project-URL: Documentation, https://github.com/michaelchen-lab/caft-llm#readme
Project-URL: Issues, https://github.com/michaelchen-lab/caft-llm/issues
Project-URL: Source, https://github.com/michaelchen-lab/caft-llm
Author-email: michaelchen-lab <michaelchenkaijie2004@gmail.com>
License-Expression: Apache-2.0
License-File: LICENSE.txt
Classifier: Development Status :: 4 - Beta
Classifier: Programming Language :: Python
Classifier: Programming Language :: Python :: 3.8
Classifier: Programming Language :: Python :: 3.9
Classifier: Programming Language :: Python :: 3.10
Classifier: Programming Language :: Python :: 3.11
Classifier: Programming Language :: Python :: 3.12
Classifier: Programming Language :: Python :: Implementation :: CPython
Classifier: Programming Language :: Python :: Implementation :: PyPy
Requires-Python: >=3.8
Requires-Dist: bitsandbytes
Requires-Dist: pandas
Requires-Dist: peft
Requires-Dist: python-dotenv
Requires-Dist: torch==2.5.1
Requires-Dist: transformers==4.51.3
Requires-Dist: wandb
Provides-Extra: train
